pyscoring/__init__.py
pyscoring/metrics/__init__.py
pyscoring/metrics/confusion_matrix.py
pyscoring/metrics/edges.py
pyscoring/metrics/intrinsic.py
pyscoring/metrics/matcher.py
pyscoring/metrics/metric.py
pyscoring/metrics/surfaces.py
pyscoring/metrics/topologics.py
pyscoring/metrics/z.py
pyscoring/metrics/metrics_helper/__init__.py
pyscoring/metrics/metrics_helper/metric_merger.py
pyscoring/utils/__init__.py
pyscoring/utils/conf.py
pyscoring/utils/launcher.py
pyscoring/utils/load.py
pyscoring-2.3.0.dist-info/licenses/LICENSE
pyscoring-2.3.0.dist-info/METADATA
pyscoring-2.3.0.dist-info/WHEEL
pyscoring-2.3.0.dist-info/top_level.txt
pyscoring-2.3.0.dist-info/RECORD
