Metadata-Version: 2.4
Name: pyscoring
Version: 2.3.0
Summary: pyscoring library : metrics for comparing vector data
Author: Etienne Le Bihan, Emmanuel Séguin, Bruno Vallet
License: GPL-3.0-or-later
License-File: LICENSE
Requires-Dist: Fiona==1.10b2
Requires-Dist: geopandas==1.0.1
Requires-Dist: networkx==3.1
Requires-Dist: numpy==1.25.2
Requires-Dist: rasterio==1.3.8
Requires-Dist: Rtree==1.0.1
Requires-Dist: scipy==1.11.1
Requires-Dist: scikit-learn==1.5.0
Requires-Dist: setuptools==70.0.0
Requires-Dist: shapely==2.0.1
Requires-Dist: six==1.16.0
Requires-Dist: threadpoolctl==3.2.0
Requires-Dist: tqdm==4.66.3
Requires-Dist: configparser==6.0.1
Requires-Dist: cjio==0.9.0
Dynamic: author
Dynamic: license
Dynamic: license-file
Dynamic: requires-dist
Dynamic: summary
